{
  "/_not-found/page": "app/_not-found/page.js",
  "/ekibimiz/page": "app/ekibimiz/page.js",
  "/haberler/page": "app/haberler/page.js",
  "/iletisim/page": "app/iletisim/page.js",
  "/cerez/page": "app/cerez/page.js",
  "/hakkimizda/page": "app/hakkimizda/page.js",
  "/gizlilik/page": "app/gizlilik/page.js",
  "/kvkk/page": "app/kvkk/page.js",
  "/referanslar/page": "app/referanslar/page.js",
  "/page": "app/page.js",
  "/haberler/[slug]/page": "app/haberler/[slug]/page.js",
  "/urunler/page": "app/urunler/page.js",
  "/servisler/page": "app/servisler/page.js",
  "/servisler/[slug]/page": "app/servisler/[slug]/page.js",
  "/urunler/[slug]/page": "app/urunler/[slug]/page.js"
}